{
    "900": {
        "key": "astro",
        "flash": true
    },
    "901": {
        "key": "beans",
        "flash": true
    },
    "902": {
        "key": "roundup",
        "music": 102,
        "flash": true
    },
    "903": {
        "key": "hydro",
        "flash": true
    },
    "904": {
        "key": "fish",
        "music": 103,
        "flash": true
    },
    "905": {
        "key": "mine",
        "music": 105,
        "flash": true
    },
    "906": {
        "key": "jetpack",
        "music": 110,
        "flash": true
    },
    "907": {
        "key": "mission1",
        "path": "quests/q1/quest.swf",
        "flash": true
    },
    "908": {
        "key": "mission2",
        "path": "quests/q2/quest.swf",
        "flash": true
    },
    "909": {
        "key": "thinice",
        "music": 111,
        "flash": true
    },
    "911": {
        "key": "mission3",
        "path": "quests/q3/quest.swf",
        "flash": true
    },
    "912": {
        "key": "waves",
        "flash": true
    },
    "913": {
        "key": "mission4",
        "path": "quests/q4/quest.swf",
        "flash": true
    },
    "914": {
        "key": "mission5",
        "path": "quests/q5/quest.swf",
        "flash": true
    },
    "915": {
        "key": "mission6",
        "path": "quests/q6/quest.swf",
        "flash": true
    },
    "916": {
        "key": "sub",
        "flash": true
    },
    "920": {
        "key": "mission7",
        "path": "quests/q7/quest.swf",
        "flash": true
    },
    "921": {
        "key": "mission8",
        "path": "quests/q8/quest.swf",
        "flash": true
    },
    "922": {
        "key": "mission9",
        "path": "quests/q9/quest.swf",
        "flash": true
    },
    "923": {
        "key": "mission10",
        "path": "quests/q10/quest.swf",
        "flash": true
    },
    "927": {
        "key": "mission11",
        "path": "quests/q11/quest.swf",
        "flash": true
    },
    "951": {
        "key": "sensei",
        "flash": false
    },
    "998": {
        "key": "card",
        "flash": false
    },
    "999": {
        "key": "sled",
        "flash": false
    }
}